[ {
  "fecha" : "2019-01-01",
  "indicativo" : "4642E",
  "nombre" : "HUELVA, RONDA ESTE",
  "provincia" : "HUELVA",
  "altitud" : 19,
  "tmed" : 11.4,
  "prec" : 0.0,
  "tmin" : 3.4,
  "horatmin" : "7:06",
  "tmax" : 19.5,
  "horatmax" : "15:45",
  "dir" : 31,
  "velmedia" : 1.4,
  "racha" : 4.4,
  "horaracha" : "19:02",
  "sol" : 7.8,
  "presMax" : 1030.4,
  "horaPresMax" : 10,
  "presMin" : 1027.2,
  "horaPresMin" : "5"
}, {
  "fecha" : "2019-01-02",
  "indicativo" : "4642E",
  "nombre" : "HUELVA, RONDA ESTE",
  "provincia" : "HUELVA",
  "altitud" : 19,
  "tmed" : 9.8,
  "prec" : 0.0,
  "tmin" : 2.2,
  "horatmin" : "7:15",
  "tmax" : 17.4,
  "horatmax" : "13:33",
  "dir" : 24,
  "velmedia" : 1.4,
  "racha" : 6.1,
  "horaracha" : "16:39",
  "sol" : 9.3,
  "presMax" : 1028.8,
  "horaPresMax" : "Varias",
  "presMin" : 1023.9,
  "horaPresMin" : "24"
}, {
  "fecha" : "2019-01-03",
  "indicativo" : "4642E",
  "nombre" : "HUELVA, RONDA ESTE",
  "provincia" : "HUELVA",
  "altitud" : 19,
  "tmed" : 10.0,
  "prec" : 0.0,
  "tmin" : 3.0,
  "horatmin" : "4:25",
  "tmax" : 17.0,
  "horatmax" : "14:39",
  "dir" : 17,
  "velmedia" : 1.1,
  "racha" : 5.8,
  "horaracha" : "14:38",
  "sol" : 3.5,
  "presMax" : 1025.9,
  "horaPresMax" : 10,
  "presMin" : 1023.1,
  "horaPresMin" : "5"
}, {
  "fecha" : "2019-01-04",
  "indicativo" : "4642E",
  "nombre" : "HUELVA, RONDA ESTE",
  "provincia" : "HUELVA",
  "altitud" : 19,
  "tmed" : 11.0,
  "prec" : 0.0,
  "tmin" : 5.2,
  "horatmin" : "Varias",
  "tmax" : 16.7,
  "horatmax" : "14:45",
  "dir" : 8,
  "velmedia" : 1.7,
  "racha" : 5.8,
  "horaracha" : "15:37",
  "sol" : 9.2,
  "presMax" : 1029.0,
  "horaPresMax" : 24,
  "presMin" : 1024.6,
  "horaPresMin" : "5"
}, {
  "fecha" : "2019-01-05",
  "indicativo" : "4642E",
  "nombre" : "HUELVA, RONDA ESTE",
  "provincia" : "HUELVA",
  "altitud" : 19,
  "tmed" : 10.4,
  "prec" : 0.0,
  "tmin" : 2.8,
  "horatmin" : "8:10",
  "tmax" : 17.9,
  "horatmax" : "15:42",
  "dir" : 10,
  "velmedia" : 1.4,
  "racha" : 5.8,
  "horaracha" : "12:14",
  "sol" : 9.4,
  "presMax" : 1031.6,
  "horaPresMax" : 10,
  "presMin" : 1028.8,
  "horaPresMin" : "24"
}, {
  "fecha" : "2019-01-06",
  "indicativo" : "4642E",
  "nombre" : "HUELVA, RONDA ESTE",
  "provincia" : "HUELVA",
  "altitud" : 19,
  "tmed" : 10.4,
  "prec" : 0.0,
  "tmin" : 2.1,
  "horatmin" : "6:25",
  "tmax" : 18.8,
  "horatmax" : "14:18",
  "dir" : 24,
  "velmedia" : 1.9,
  "racha" : 5.3,
  "horaracha" : "17:20",
  "sol" : 9.4,
  "presMax" : 1029.5,
  "horaPresMax" : 10,
  "presMin" : 1026.1,
  "horaPresMin" : "16"
}, {
  "fecha" : "2019-01-07",
  "indicativo" : "4642E",
  "nombre" : "HUELVA, RONDA ESTE",
  "provincia" : "HUELVA",
  "altitud" : 19,
  "tmed" : 9.2,
  "prec" : 0.0,
  "tmin" : 0.4,
  "horatmin" : "6:15",
  "tmax" : 18.1,
  "horatmax" : "15:40",
  "dir" : 3,
  "velmedia" : 1.4,
  "racha" : 3.6,
  "horaracha" : "0:26",
  "sol" : 9.4,
  "presMax" : 1027.9,
  "horaPresMax" : 11,
  "presMin" : 1024.6,
  "horaPresMin" : "Varias"
}, {
  "fecha" : "2019-01-08",
  "indicativo" : "4642E",
  "nombre" : "HUELVA, RONDA ESTE",
  "provincia" : "HUELVA",
  "altitud" : 19,
  "tmed" : 9.8,
  "prec" : 0.0,
  "tmin" : 1.3,
  "horatmin" : "6:45",
  "tmax" : 18.3,
  "horatmax" : "15:46",
  "dir" : 8,
  "velmedia" : 1.9,
  "racha" : 4.4,
  "horaracha" : "12:04",
  "sol" : 9.4,
  "presMax" : 1028.1,
  "horaPresMax" : 10,
  "presMin" : 1023.3,
  "horaPresMin" : "24"
}, {
  "fecha" : "2019-01-09",
  "indicativo" : "4642E",
  "nombre" : "HUELVA, RONDA ESTE",
  "provincia" : "HUELVA",
  "altitud" : 19,
  "tmed" : 9.6,
  "prec" : 0.0,
  "tmin" : 1.4,
  "horatmin" : "7:30",
  "tmax" : 17.8,
  "horatmax" : "14:50",
  "dir" : 28,
  "velmedia" : 1.7,
  "racha" : 5.3,
  "horaracha" : "18:59",
  "sol" : 9.4,
  "presMax" : 1023.3,
  "horaPresMax" : 0,
  "presMin" : 1015.5,
  "horaPresMin" : "24"
}, {
  "fecha" : "2019-01-10",
  "indicativo" : "4642E",
  "nombre" : "HUELVA, RONDA ESTE",
  "provincia" : "HUELVA",
  "altitud" : 19,
  "tmed" : 9.4,
  "prec" : 0.0,
  "tmin" : 2.3,
  "horatmin" : "6:40",
  "tmax" : 16.4,
  "horatmax" : "Varias",
  "dir" : 9,
  "velmedia" : 1.9,
  "racha" : 7.5,
  "horaracha" : "11:08",
  "sol" : 9.4,
  "presMax" : 1018.8,
  "horaPresMax" : 24,
  "presMin" : 1014.5,
  "horaPresMin" : "5"
}, {
  "fecha" : "2019-01-11",
  "indicativo" : "4642E",
  "nombre" : "HUELVA, RONDA ESTE",
  "provincia" : "HUELVA",
  "altitud" : 19,
  "tmed" : 8.9,
  "prec" : 0.0,
  "tmin" : 3.2,
  "horatmin" : "8:00",
  "tmax" : 14.6,
  "horatmax" : "15:10",
  "dir" : 8,
  "velmedia" : 2.5,
  "racha" : 11.1,
  "horaracha" : "11:37",
  "sol" : 9.5,
  "presMax" : 1025.1,
  "horaPresMax" : 23,
  "presMin" : 1018.7,
  "horaPresMin" : "0"
}, {
  "fecha" : "2019-01-12",
  "indicativo" : "4642E",
  "nombre" : "HUELVA, RONDA ESTE",
  "provincia" : "HUELVA",
  "altitud" : 19,
  "tmed" : 8.8,
  "prec" : 0.0,
  "tmin" : 2.0,
  "horatmin" : "6:45",
  "tmax" : 15.7,
  "horatmax" : "15:05",
  "dir" : 8,
  "velmedia" : 2.8,
  "racha" : 8.3,
  "horaracha" : "13:21",
  "sol" : 9.5,
  "presMax" : 1027.0,
  "horaPresMax" : 11,
  "presMin" : 1024.5,
  "horaPresMin" : "Varias"
}, {
  "fecha" : "2019-01-13",
  "indicativo" : "4642E",
  "nombre" : "HUELVA, RONDA ESTE",
  "provincia" : "HUELVA",
  "altitud" : 19,
  "tmed" : 9.4,
  "prec" : 0.0,
  "tmin" : 0.7,
  "horatmin" : "6:30",
  "tmax" : 18.0,
  "horatmax" : "16:08",
  "dir" : 99,
  "velmedia" : 1.9,
  "racha" : 6.1,
  "horaracha" : "Varias",
  "sol" : 9.5,
  "presMax" : 1027.3,
  "horaPresMax" : 10,
  "presMin" : 1023.3,
  "horaPresMin" : "16"
}, {
  "fecha" : "2019-01-14",
  "indicativo" : "4642E",
  "nombre" : "HUELVA, RONDA ESTE",
  "provincia" : "HUELVA",
  "altitud" : 19,
  "tmed" : 9.4,
  "prec" : 0.0,
  "tmin" : 0.6,
  "horatmin" : "7:54",
  "tmax" : 18.1,
  "horatmax" : "15:28",
  "dir" : 24,
  "velmedia" : 2.5,
  "racha" : 5.3,
  "horaracha" : "17:06",
  "sol" : 9.5,
  "presMax" : 1023.8,
  "horaPresMax" : 0,
  "presMin" : 1018.9,
  "horaPresMin" : "Varias"
}, {
  "fecha" : "2019-01-15",
  "indicativo" : "4642E",
  "nombre" : "HUELVA, RONDA ESTE",
  "provincia" : "HUELVA",
  "altitud" : 19,
  "tmed" : 8.7,
  "prec" : 0.0,
  "tmin" : 1.3,
  "horatmin" : "6:00",
  "tmax" : 16.1,
  "horatmax" : "15:35",
  "dir" : 36,
  "velmedia" : 1.1,
  "racha" : 4.2,
  "horaracha" : "0:52",
  "sol" : 5.0,
  "presMax" : 1020.3,
  "horaPresMax" : 10,
  "presMin" : 1017.8,
  "horaPresMin" : "5"
}, {
  "fecha" : "2019-01-16",
  "indicativo" : "4642E",
  "nombre" : "HUELVA, RONDA ESTE",
  "provincia" : "HUELVA",
  "altitud" : 19,
  "tmed" : 10.7,
  "prec" : 0.0,
  "tmin" : 4.1,
  "horatmin" : "6:40",
  "tmax" : 17.3,
  "horatmax" : "14:00",
  "dir" : 19,
  "velmedia" : 1.4,
  "racha" : 4.7,
  "horaracha" : "15:14",
  "sol" : 8.5,
  "presMax" : 1019.2,
  "horaPresMax" : 0,
  "presMin" : 1015.7,
  "horaPresMin" : "16"
}, {
  "fecha" : "2019-01-17",
  "indicativo" : "4642E",
  "nombre" : "HUELVA, RONDA ESTE",
  "provincia" : "HUELVA",
  "altitud" : 19,
  "tmed" : 11.4,
  "prec" : 0.0,
  "tmin" : 5.7,
  "horatmin" : "6:30",
  "tmax" : 17.0,
  "horatmax" : "15:35",
  "dir" : 35,
  "velmedia" : 2.5,
  "racha" : 7.5,
  "horaracha" : "23:31",
  "sol" : 4.7,
  "presMax" : 1018.4,
  "horaPresMax" : 24,
  "presMin" : 1015.1,
  "horaPresMin" : "15"
}, {
  "fecha" : "2019-01-18",
  "indicativo" : "4642E",
  "nombre" : "HUELVA, RONDA ESTE",
  "provincia" : "HUELVA",
  "altitud" : 19,
  "tmed" : 10.7,
  "prec" : 3.8,
  "tmin" : 4.7,
  "horatmin" : "7:50",
  "tmax" : 16.7,
  "horatmax" : "14:00",
  "dir" : 35,
  "velmedia" : 2.2,
  "racha" : 8.9,
  "horaracha" : "5:57",
  "sol" : 8.6,
  "presMax" : 1020.3,
  "horaPresMax" : 11,
  "presMin" : 1017.5,
  "horaPresMin" : "5"
}, {
  "fecha" : "2019-01-19",
  "indicativo" : "4642E",
  "nombre" : "HUELVA, RONDA ESTE",
  "provincia" : "HUELVA",
  "altitud" : 19,
  "tmed" : 11.4,
  "prec" : 4.6,
  "tmin" : 8.6,
  "horatmin" : "Varias",
  "tmax" : 14.3,
  "horatmax" : "18:36",
  "dir" : 24,
  "velmedia" : 1.7,
  "racha" : 12.2,
  "horaracha" : "20:08",
  "sol" : 0.3,
  "presMax" : 1018.8,
  "horaPresMax" : 11,
  "presMin" : 1011.4,
  "horaPresMin" : "23"
}, {
  "fecha" : "2019-01-20",
  "indicativo" : "4642E",
  "nombre" : "HUELVA, RONDA ESTE",
  "provincia" : "HUELVA",
  "altitud" : 19,
  "tmed" : 12.2,
  "prec" : 0.0,
  "tmin" : 8.3,
  "horatmin" : "23:00",
  "tmax" : 16.1,
  "horatmax" : "15:35",
  "dir" : 30,
  "velmedia" : 4.4,
  "racha" : 11.9,
  "horaracha" : "15:19",
  "sol" : 8.5,
  "presMax" : 1019.0,
  "horaPresMax" : 24,
  "presMin" : 1010.7,
  "horaPresMin" : "4"
}, {
  "fecha" : "2019-01-21",
  "indicativo" : "4642E",
  "nombre" : "HUELVA, RONDA ESTE",
  "provincia" : "HUELVA",
  "altitud" : 19,
  "tmed" : 11.0,
  "tmin" : 4.8,
  "horatmin" : "7:06",
  "tmax" : 17.2,
  "horatmax" : "14:57",
  "dir" : 36,
  "velmedia" : 1.7,
  "racha" : 7.8,
  "horaracha" : "21:24",
  "sol" : 9.2,
  "presMax" : 1021.9,
  "horaPresMax" : 23,
  "presMin" : 1018.5,
  "horaPresMin" : "4"
}, {
  "fecha" : "2019-01-22",
  "indicativo" : "4642E",
  "nombre" : "HUELVA, RONDA ESTE",
  "provincia" : "HUELVA",
  "altitud" : 19,
  "tmed" : 9.3,
  "prec" : 0.0,
  "tmin" : 3.9,
  "horatmin" : "5:53",
  "tmax" : 14.7,
  "horatmax" : "14:43",
  "dir" : 30,
  "velmedia" : 3.1,
  "racha" : 12.8,
  "horaracha" : "13:31",
  "sol" : 4.2,
  "presMax" : 1021.9,
  "horaPresMax" : 10,
  "presMin" : 1017.5,
  "horaPresMin" : "23"
}, {
  "fecha" : "2019-01-23",
  "indicativo" : "4642E",
  "nombre" : "HUELVA, RONDA ESTE",
  "provincia" : "HUELVA",
  "altitud" : 19,
  "tmed" : 12.8,
  "prec" : 0.0,
  "tmin" : 8.4,
  "horatmin" : "7:40",
  "tmax" : 17.1,
  "horatmax" : "14:45",
  "dir" : 30,
  "velmedia" : 5.8,
  "racha" : 16.9,
  "horaracha" : "12:57",
  "sol" : 7.6,
  "presMax" : 1017.8,
  "horaPresMax" : 0,
  "presMin" : 1014.0,
  "horaPresMin" : "Varias"
}, {
  "fecha" : "2019-01-24",
  "indicativo" : "4642E",
  "nombre" : "HUELVA, RONDA ESTE",
  "provincia" : "HUELVA",
  "altitud" : 19,
  "tmed" : 15.9,
  "prec" : 0.0,
  "tmin" : 11.4,
  "horatmin" : "3:30",
  "tmax" : 20.4,
  "horatmax" : "15:40",
  "dir" : 99,
  "velmedia" : 2.8,
  "racha" : 9.7,
  "horaracha" : "Varias",
  "sol" : 8.4,
  "presMax" : 1014.4,
  "horaPresMax" : 0,
  "presMin" : 1010.7,
  "horaPresMin" : "14"
}, {
  "fecha" : "2019-01-25",
  "indicativo" : "4642E",
  "nombre" : "HUELVA, RONDA ESTE",
  "provincia" : "HUELVA",
  "altitud" : 19,
  "tmed" : 14.0,
  "prec" : 0.0,
  "tmin" : 6.7,
  "horatmin" : "6:40",
  "tmax" : 21.4,
  "horatmax" : "16:10",
  "dir" : 9,
  "velmedia" : 1.7,
  "racha" : 5.3,
  "horaracha" : "14:08",
  "sol" : 9.8,
  "presMax" : 1017.2,
  "horaPresMax" : 11,
  "presMin" : 1013.5,
  "horaPresMin" : "2"
}, {
  "fecha" : "2019-01-26",
  "indicativo" : "4642E",
  "nombre" : "HUELVA, RONDA ESTE",
  "provincia" : "HUELVA",
  "altitud" : 19,
  "tmed" : 13.5,
  "prec" : 0.0,
  "tmin" : 5.5,
  "horatmin" : "7:27",
  "tmax" : 21.5,
  "horatmax" : "14:09",
  "dir" : 20,
  "velmedia" : 2.5,
  "racha" : 6.7,
  "horaracha" : "15:26",
  "sol" : 9.9,
  "presMax" : 1019.3,
  "horaPresMax" : 11,
  "presMin" : 1016.7,
  "horaPresMin" : "Varias"
}, {
  "fecha" : "2019-01-27",
  "indicativo" : "4642E",
  "nombre" : "HUELVA, RONDA ESTE",
  "provincia" : "HUELVA",
  "altitud" : 19,
  "tmed" : 10.9,
  "prec" : 0.0,
  "tmin" : 5.7,
  "horatmin" : "4:30",
  "tmax" : 16.1,
  "horatmax" : "14:10",
  "dir" : 29,
  "velmedia" : 3.3,
  "racha" : 15.8,
  "horaracha" : "14:19",
  "sol" : 8.7,
  "presMax" : 1021.6,
  "horaPresMax" : 24,
  "presMin" : 1016.8,
  "horaPresMin" : "4"
}, {
  "fecha" : "2019-01-28",
  "indicativo" : "4642E",
  "nombre" : "HUELVA, RONDA ESTE",
  "provincia" : "HUELVA",
  "altitud" : 19,
  "tmed" : 11.7,
  "prec" : 0.0,
  "tmin" : 7.1,
  "horatmin" : "7:19",
  "tmax" : 16.3,
  "horatmax" : "13:06",
  "dir" : 30,
  "velmedia" : 4.2,
  "racha" : 12.2,
  "horaracha" : "15:37",
  "sol" : 6.8,
  "presMax" : 1022.8,
  "horaPresMax" : 12,
  "presMin" : 1020.7,
  "horaPresMin" : "5"
}, {
  "fecha" : "2019-01-29",
  "indicativo" : "4642E",
  "nombre" : "HUELVA, RONDA ESTE",
  "provincia" : "HUELVA",
  "altitud" : 19,
  "tmed" : 13.0,
  "prec" : 0,
  "tmin" : 8.1,
  "horatmin" : "4:35",
  "tmax" : 17.8,
  "horatmax" : "14:10",
  "dir" : 29,
  "velmedia" : 4.4,
  "racha" : 11.7,
  "horaracha" : "14:12",
  "sol" : 2.4,
  "presMax" : 1021.4,
  "horaPresMax" : 11,
  "presMin" : 1017.3,
  "horaPresMin" : "17"
}, {
  "fecha" : "2019-01-30",
  "indicativo" : "4642E",
  "nombre" : "HUELVA, RONDA ESTE",
  "provincia" : "HUELVA",
  "altitud" : 19,
  "tmed" : 12.7,
  "prec" : 2.4,
  "tmin" : 11.1,
  "horatmin" : "1:12",
  "tmax" : 14.3,
  "horatmax" : "13:58",
  "dir" : 26,
  "velmedia" : 2.8,
  "racha" : 7.8,
  "horaracha" : "23:54",
  "sol" : 0.0,
  "presMax" : 1017.6,
  "horaPresMax" : 0,
  "presMin" : 1012.0,
  "horaPresMin" : "24"
}, {
  "fecha" : "2019-01-31",
  "indicativo" : "4642E",
  "nombre" : "HUELVA, RONDA ESTE",
  "provincia" : "HUELVA",
  "altitud" : 19,
  "tmed" : 15.4,
  "tmin" : 13.4,
  "horatmin" : "Varias",
  "tmax" : 17.3,
  "horatmax" : "Varias",
  "dir" : 25,
  "velmedia" : 6.7,
  "racha" : 15.3,
  "horaracha" : "13:42",
  "sol" : 3.4,
  "presMax" : 1012.0,
  "horaPresMax" : 0,
  "presMin" : 1002.8,
  "horaPresMin" : "24"
} ]
